{
  "type": "Feature",
  "properties": {
    "iso:country":"BR",
    "sg:address":"Av. Eng. Luis Carlos Berrini 1500  CJ 111 Brooklin Novo",
    "sg:city":"S\u00e3o Paulo",
    "sg:classifiers":[
        {
            "category":"Professional",
            "subcategory":"Computer Services",
            "type":"Services"
        }
    ],
    "sg:postcode":"04571-000",
    "sg:tags":[
        "isp",
        "internet",
        "colocation",
        "hosting",
        "professional-services"
    ],
    "sg:website":"http://www.value4.net",
    "wof:name":"Value For Networks",
    "wof:placetype":"venue"
},
  "geometry": {"coordinates":[-46.6946978,-23.6100216],"type":"Point"}
}