{
  "type": "Feature",
  "properties": {
    "iso:country":"BR",
    "sg:address":"Rua da Quitanda, 67, Sala 302 Centro",
    "sg:city":"Rio de Janeiro",
    "sg:classifiers":[
        {
            "category":"Manufacturing",
            "subcategory":"Electronics",
            "type":"Manufacturing & Wholesale Goods"
        }
    ],
    "sg:postcode":"CEP 20011-030",
    "sg:tags":[
        "audience-response-system",
        "voting-system",
        "wireless-voting-system",
        "voting-keypad",
        "group-response-system",
        "student-response-system"
    ],
    "sg:website":"http://www.powervote.com",
    "wof:name":"PowerVote",
    "wof:placetype":"venue"
},
  "geometry": {"coordinates":[-43.1769491,-22.9033786],"type":"Point"}
}