{
  "type": "Feature",
  "properties": {
    "iso:country":"BR",
    "sg:address":"R. Luiz Carlos Prestes, 180 3\u00ba Floor Barra da Tijuca",
    "sg:city":"Rio de Janeiro",
    "sg:classifiers":[
        {
            "category":"Professional",
            "subcategory":"Computer Services",
            "type":"Services"
        }
    ],
    "sg:postcode":"22775-055",
    "sg:tags":[
        "isp",
        "internet",
        "colocation",
        "hosting",
        "professional-services"
    ],
    "sg:website":"http://www.value4.net",
    "wof:name":"Value For Networks",
    "wof:placetype":"venue"
},
  "geometry": {"coordinates":[-43.5793559,-22.8748766],"type":"Point"}
}